setup.py
digEntityMerger/__init__.py
digEntityMerger/basicMerger.py
digEntityMerger/cleaner.py
digEntityMerger/convertToSeq.py
digEntityMerger/create_base_file.py
digEntityMerger/deduplicator.py
digEntityMerger/fileUtil.py
digEntityMerger/framer.py
digEntityMerger/generateSelfMerge.py
digEntityMerger/jsonUtil.py
digEntityMerger/merger.py
digEntityMerger.egg-info/PKG-INFO
digEntityMerger.egg-info/SOURCES.txt
digEntityMerger.egg-info/dependency_links.txt
digEntityMerger.egg-info/requires.txt
digEntityMerger.egg-info/top_level.txt