Metadata-Version: 1.1
Name: digEntityMerger
Version: 0.3
Summary: digEntityMerger
Home-page: https://github.com/usc-isi-i2/dig-entity-merger
Author: Dipsy Kapoor
Author-email: dipsykapoor@gmail.com
License: UNKNOWN
Download-URL: https://github.com/usc-isi-i2/dig-entity-merger
Platform: UNKNOWN
